{

    "url": "http://allbasketball.ru/teams/{0}.html",

    "scrapPeriodInHour": 8,

    "teams": ["Miami Heat", "Indiana Pacers", "Atlanta Hawks", "Philadelphia 76ers", "Toronto Raptors", "Chicago Bulls", "Washington Wizards",
        "Detroit Pistons", "Brooklyn Nets", "Charlotte Bobcats", "New York Knicks", "Cleveland Cavaliers", "Boston Celtics", "Orlando Magic",
        "Milwaukee Bucks", "San Antonio Spurs", "Oklahoma City Thunder", "Portland Trail Blazers", "Los Angeles Clippers", "Golden State Warriors",
        "Houston Rockets", "Phoenix Suns", "Dallas Mavericks", "Denver Nuggets", "Minnesota Timberwolves", "Memphis Grizzlies", "New Orleans Pelicans",
        "Los Angeles Lakers", "Sacramento Kings", "Utah Jazz"],

    "statCollection": "scrapStat",
    "recentCollection": "recent",

    "security": false
}